ocpp-stubs/__init__.pyi
ocpp-stubs/routing.pyi
ocpp_stubs-0.17.0.post1.dist-info/METADATA
ocpp_stubs-0.17.0.post1.dist-info/WHEEL
ocpp_stubs-0.17.0.post1.dist-info/top_level.txt
ocpp_stubs-0.17.0.post1.dist-info/RECORD
