Metadata-Version: 2.1
Name: ocpp-stubs
Version: 0.17.0.post1
Author-email: "Hugo O. Rivera" <hugo.rivera@powerflex.com>
Project-URL: repository, https://github.com/edf-re/ocpp-stubs
Classifier: Programming Language :: Python :: 3
Classifier: Programming Language :: Python :: 3.10
Classifier: Programming Language :: Python :: 3.9
Classifier: Programming Language :: Python :: 3.8
Classifier: Programming Language :: Python :: 3.7
Requires-Dist: ocpp (<0.18,>=0.17)
Requires-Dist: typing-extensions ; python_version < "3.10"
